Metadata-Version: 2.1
Name: mgzip
Version: 0.2.0
Summary: A multi-threading implementation of Python gzip module
Home-page: https://github.com/vinlyx/mgzip
Author: Vincent Li
Author-email: vincentliyx@gmail.com
License: MIT
Platform: UNKNOWN
Classifier: Development Status :: 4 - Beta
Classifier: License :: OSI Approved :: MIT License
Classifier: Operating System :: OS Independent
Classifier: Programming Language :: Python :: 3
Classifier: Programming Language :: Python :: Implementation :: CPython
Classifier: Topic :: Software Development :: Libraries :: Python Modules
Classifier: Intended Audience :: Developers
Requires-Python: >=3.6
